transportlib/__init__.py
transportlib/config.py
transportlib/utils.py
transportlib/transport/__init__.py
transportlib/transport/postgres_transport.py
transportlib/transport/yfinance_transport/__init__.py
transportlib/transport/yfinance_transport/stock_price.py
transportlib-0.1.3.dist-info/METADATA
transportlib-0.1.3.dist-info/WHEEL
transportlib-0.1.3.dist-info/top_level.txt
transportlib-0.1.3.dist-info/RECORD
