Metadata-Version: 2.1
Name: transportlib
Version: 0.1.3
Summary: A library for reusable transport utilities
Home-page: https://github.com/kenho811/flux_infra
Author: Ken Ho
Author-email: kenho811@gmail.com
License: proprietary
Project-URL: Source Code, https://github.com/kenho811/flux_infra
Project-URL: PyPI, https://pypi.org/project/transportlib/
Classifier: Programming Language :: Python :: 3
Requires-Python: >=3.7.*
Requires-Dist: appdirs (==1.4.4)
Requires-Dist: attrs (==22.1.0)
Requires-Dist: certifi (==2022.9.24)
Requires-Dist: charset-normalizer (==2.1.1)
Requires-Dist: exceptiongroup (==1.0.1)
Requires-Dist: idna (==3.4)
Requires-Dist: iniconfig (==1.1.1)
Requires-Dist: lxml (==4.9.1)
Requires-Dist: multitasking (==0.0.11)
Requires-Dist: numpy (==1.23.4)
Requires-Dist: packaging (==21.3)
Requires-Dist: pandas (==1.5.1)
Requires-Dist: pluggy (==1.0.0)
Requires-Dist: psycopg2 (==2.9.5)
Requires-Dist: pyparsing (==3.0.9)
Requires-Dist: pytest (==7.2.0)
Requires-Dist: python-dateutil (==2.8.2)
Requires-Dist: pytz (==2022.6)
Requires-Dist: PyYAML (==6.0)
Requires-Dist: requests (==2.28.1)
Requires-Dist: six (==1.16.0)
Requires-Dist: tomli (==2.0.1)
Requires-Dist: urllib3 (==1.26.12)
Requires-Dist: yfinance (==0.1.85)
